v2f/__init__.py
v2f/cli.py
v2f/functions.py
v2f/parser.py
vcf2fasta-0.1.3.dist-info/licenses/LICENSE
vcf2fasta-0.1.3.dist-info/METADATA
vcf2fasta-0.1.3.dist-info/WHEEL
vcf2fasta-0.1.3.dist-info/entry_points.txt
vcf2fasta-0.1.3.dist-info/top_level.txt
vcf2fasta-0.1.3.dist-info/RECORD
