Metadata-Version: 2.4
Name: vcf2fasta
Version: 0.1.3
Summary: A package to convert VCF files to FASTA format.
Author-email: Santiago Sanchez <santiago.sanchez@gmail.com>
License: MIT License
Project-URL: Homepage, https://github.com/santiagosnchez/vcf2fasta
Project-URL: Repository, https://github.com/santiagosnchez/vcf2fasta
Keywords: vcf,fasta,bioinformatics,genomics
Classifier: Programming Language :: Python :: 3
Classifier: License :: OSI Approved :: MIT License
Classifier: Operating System :: OS Independent
Requires-Python: >=3.10
License-File: LICENSE
Requires-Dist: pysam
Requires-Dist: art
Dynamic: license-file
